{"stat.chestOpened":7,"stat.pickup.rustic.wildberry_bush":4,"stat.pickup.minecraft.bone":23,"stat.leaveGame":2,"stat.pickup.minecraft.gravel":40,"stat.pickup.minecraft.arrow":6,"stat.mineBlock.minecraft.cobblestone":10,"stat.pickup.minecraft.stone_pickaxe":2,"stat.pickup.minecraft.wooden_pressure_plate":1,"stat.pickup.minecraft.flint":9,"maka.kill":3,"stat.pickup.minecraft.stone_axe":1,"stat.mineBlock.minecraft.deadbush":2,"stat.pickup.roughtweaks.bandage":2,"stat.drop.minecraft.flint":4,"stat.pickup.notreepunching.axe/flint":3,"stat.craftItem.minecraft.wool":3,"geist.kill":1,"stat.useItem.notreepunching.rock/stone":1,"stat.craftItem.notreepunching.grass_string":14,"stat.drop.lycanitesmobs.raw_maka_meat":1,"stat.mineBlock.iceandfire.fire_lily":1,"stat.swimOneCm":21613,"stat.jump":960,"stat.useItem.minecraft.sand":10,"stat.pickup.minecraft.fence":2,"stat.climbOneCm":2817,"stat.fallOneCm":16713,"stat.useItem.minecraft.planks":16,"stat.pickup.minecraft.glowstone_dust":10,"stat.useItem.minecraft.stone_axe":17,"stat.drop.minecraft.stone_sword":1,"stat.useItem.notreepunching.axe/flint":32,"stat.pickup.minecraft.porkchop":3,"stat.pickup.minecraft.gunpowder":3,"stat.crouchOneCm":42666,"stat.drop.minecraft.brown_mushroom":1,"stat.drop.notreepunching.grass_string":5,"stat.pickup.minecraft.dirt":38,"stat.useItem.minecraft.dirt":2,"stat.useItem.minecraft.stone_slab2":11,"stat.craftingTableInteraction":16,"stat.pickup.minecraft.rotten_flesh":10,"stat.craftItem.mujmajnkraftsbettersurvival.itemstonedagger":2,"stat.pickup.minecraft.sand":24,"roc.kill":4,"stat.pickup.notreepunching.rock/sandstone":1,"jengu.kill":1,"stat.mineBlock.minecraft.iron_bars":1,"stat.craftItem.minecraft.stone_axe":1,"stat.damageTaken":3880,"stat.pickup.minecraft.feather":11,"stat.pickup.notreepunching.knife/flint":6,"stat.pickup.minecraft.leather":11,"stat.pickup.rustic.cohosh":2,"stat.pickup.notreepunching.pickaxe/flint":5,"stat.pickup.notreepunching.rock/stone":5,"stat.pickup.lycanitesmobs.raw_maka_meat":11,"stat.craftItem.minecraft.stone_pickaxe":2,"stat.drop.notreepunching.flint_shard":1,"stat.pickup.minecraft.cobblestone":45,"stat.pickup.minecraft.planks":55,"stat.pickup.lycanitesmobs.aquapulsecharge":1,"stat.flyOneCm":115828,"stat.drop.notreepunching.knife/flint":1,"stat.pickup.minecraft.wheat_seeds":101,"stat.pickup.minecraft.brown_mushroom":7,"stat.mineBlock.minecraft.sand":17,"stat.useItem.notreepunching.pickaxe/flint":16,"stat.pickup.minecraft.oak_stairs":2,"stat.entityKilledBy.Zombie":1,"stat.drop.minecraft.sand":5,"stat.mineBlock.minecraft.gravel":44,"stat.useItem.minecraft.stone_pickaxe":9,"stat.pickup.iceandfire.fire_lily":2,"stat.craftItem.notreepunching.pickaxe/flint":1,"stat.craftItem.minecraft.cooked_fish":2,"stat.pickup.quark.tallow":3,"stat.damageDealt":2806,"stat.sleepInBed":1,"stat.timeSinceDeath":3367,"stat.mineBlock.minecraft.dirt":10,"stat.drop.notreepunching.axe/flint":2,"stat.mineBlock.rustic.cohosh":1,"stat.pickup.minecraft.mutton":11,"stat.mineBlock.minecraft.monster_egg":4,"stat.walkOneCm":279080,"stat.craftItem.minecraft.bed":2,"stat.drop.notreepunching.rock/sandstone":1,"stat.pickup.minecraft.stick":96,"stat.useItem.notreepunching.knife/flint":105,"stat.craftItem.simpledifficulty.canteen":1,"stat.useItem.minecraft.log":9,"stat.pickup.minecraft.crafting_table":1,"stat.pickup.rustic.wildberries":2,"stat.useItem.minecraft.cobblestone":7,"stat.furnaceInteraction":2,"stat.craftItem.minecraft.crafting_table":1,"stat.useItem.minecraft.gravel":21,"stat.mineBlock.minecraft.double_plant":7,"stat.drop.iceandfire.fire_lily":1,"stat.pickup.minecraft.log":43,"stat.useItem.minecraft.cooked_fish":2,"stat.pickup.notreepunching.grass_fiber":92,"stat.entityKilledBy.Skeleton":6,"stat.sprintOneCm":91347,"stat.pickup.minecraft.ladder":21,"stat.pickup.notreepunching.flint_shard":18,"stat.killEntity.Skeleton":2,"stat.mineBlock.minecraft.crafting_table":1,"stat.pickup.minecraft.stone_sword":1,"stat.mobKills":16,"stat.pickup.dynamictrees.oakseed":2,"stat.mineBlock.minecraft.log":9,"stat.pickup.notreepunching.grass_string":27,"stat.mineBlock.minecraft.oak_stairs":1,"stat.pickup.simpledifficulty.canteen":1,"stat.deaths":17,"stat.mineBlock.minecraft.planks":15,"stat.pickup.lycanitesmobs.geistliver":4,"stat.craftItem.notreepunching.axe/flint":3,"stat.drop":19,"stat.pickup.lycanitesmobs.cleansingcrystal":2,"stat.playOneMinute":71675,"stat.killEntity.Sheep":7,"stat.pickup.minecraft.red_flower":3,"stat.useItem.minecraft.ladder":16,"stat.sneakTime":9358,"stat.pickup.minecraft.wool":6,"stat.killEntity.Zombie":1,"stat.pickup.minecraft.iron_bars":2,"stat.craftItem.notreepunching.knife/flint":2,"stat.craftItem.minecraft.cobblestone":1,"stat.mineBlock.minecraft.tallgrass":145,"stat.diveOneCm":53242,"stat.useItem.mujmajnkraftsbettersurvival.itemstonedagger":23}